{
  "categories": {
    "sport_loisirs": {
      "hasAttributes": false,
      "level": 1,
      "name": "Sport & Loisirs",
      "parentId": null
    },
    "vetements_sport": {
      "hasAttributes": false,
      "level": 2,
      "name": "Vêtements de sport",
      "parentId": "sport_loisirs"
    },
    "vetements_sport_homme": {
      "hasAttributes": false,
      "level": 3,
      "name": "Vêtements de sport Hommes",
      "parentId": "vetements_sport"
    },
    "vestes_manteaux_sport_homme": {
      "hasAttributes": false,
      "level": 4,
      "name": "Vestes et manteaux de sport",
      "parentId": "vetements_sport_homme"
    },
    "joggings_survetements_sport_homme": {
      "hasAttributes": false,
      "level": 4,
      "name": "Joggings & Survêtements de sport",
      "parentId": "vetements_sport_homme"
    },
    "maillots_equipe_sport_homme": {
      "hasAttributes": false,
      "level": 4,
      "name": "Maillots d'équipe de sport",
      "parentId": "vetements_sport_homme"
    },
    "accessoires_sport_homme": {
      "hasAttributes": false,
      "level": 4,
      "name": "Accessoires de sport homme",
      "parentId": "vetements_sport_homme"
    },
    "chaussettes_sport_homme": {
      "hasAttributes": false,
      "level": 4,
      "name": "Chaussettes de sport homme",
      "parentId": "vetements_sport_homme"
    },
    "base_layers_compression_homme": {
      "hasAttributes": false,
      "level": 4,
      "name": "Base layers et compression de sport homme",
      "parentId": "vetements_sport_homme"
    },
    "pulls_polaires_sport_homme": {
      "hasAttributes": false,
      "level": 4,
      "name": "Pulls et polaires de sport homme",
      "parentId": "vetements_sport_homme"
    },
    "shorts_pantalons_sport_homme": {
      "hasAttributes": false,
      "level": 4,
      "name": "Shorts et pantalons de sport homme",
      "parentId": "vetements_sport_homme"
    },
    "sous_vetements_sport_homme": {
      "hasAttributes": false,
      "level": 4,
      "name": "Sous-vêtements de sport homme",
      "parentId": "vetements_sport_homme"
    },
    "tshirts_sport_homme": {
      "hasAttributes": false,
      "level": 4,
      "name": "T-shirts, chemises et polos de sport homme",
      "parentId": "vetements_sport_homme"
    },
    "vetements_exterieur_sport_homme": {
      "hasAttributes": false,
      "level": 4,
      "name": "Vêtements d'extérieur homme",
      "parentId": "vetements_sport_homme"
    },
    "vetements_pluie_homme": {
      "hasAttributes": false,
      "level": 4,
      "name": "Vêtements de pluie homme",
      "parentId": "vetements_sport_homme"
    },
    "vetements_natation_homme": {
      "hasAttributes": false,
      "level": 4,
      "name": "Vêtements mer et natation homme",
      "parentId": "vetements_sport_homme"
    },
    "vetements_sport_femme": {
      "hasAttributes": false,
      "level": 3,
      "name": "Vêtements de sport Femmes",
      "parentId": "vetements_sport"
    },
    "accessoires_sport_femme": {
      "hasAttributes": false,
      "level": 4,
      "name": "Accessoires de sport femme",
      "parentId": "vetements_sport_femme"
    },
    "chaussettes_sport_femme": {
      "hasAttributes": false,
      "level": 4,
      "name": "Chaussettes de sport femme",
      "parentId": "vetements_sport_femme"
    },
    "base_layers_compression_femme": {
      "hasAttributes": false,
      "level": 4,
      "name": "Base layers et compression de sport femme",
      "parentId": "vetements_sport_femme"
    },
    "jupes_shorts_sport_femme": {
      "hasAttributes": false,
      "level": 4,
      "name": "Jupes et jupes-shorts de sport femme",
      "parentId": "vetements_sport_femme"
    },
    "pulls_polaires_sport_femme": {
      "hasAttributes": false,
      "level": 4,
      "name": "Pulls et polaires de sport femme",
      "parentId": "vetements_sport_femme"
    },
    "robes_sport_femme": {
      "hasAttributes": false,
      "level": 4,
      "name": "Robes de sport femme",
      "parentId": "vetements_sport_femme"
    },
    "shorts_pantalons_sport_femme": {
      "hasAttributes": false,
      "level": 4,
      "name": "Shorts et pantalons de sport femme",
      "parentId": "vetements_sport_femme"
    }
  }
}
